{"authors.": {"authors": ["Michael Pyne", "David Faure", "KDE Scripty", "Stephan Kulow", "Dirk Mueller", "Raphael Kubo da Costa", "Laurent Montel", "\u00c0lex Fiestas", "yurchor", "Alex Merry"], "commits": [1243, 80, 71, 40, 39, 23, 20, 12, 10, 9], "id": [336, 4, 10, 2, 13, 325, 7, 78, 152, 146]}, "authors.last month": {"authors": ["Michael Pyne", "Laurent Montel", "David Edmundson", "David Faure", "Martin Gr\u00e4\u00dflin"], "commits": [6, 3, 2, 1, 1], "id": [336, 7, 340, 4, 159]}, "authors.last year": {"authors": ["Michael Pyne", "David Faure", "\u00c0lex Fiestas", "Alex Merry", "KDE Scripty", "Laurent Montel", "David Edmundson", "Ivan \u010cuki\u0107", "Martin Gr\u00e4\u00dflin", "Martin Klapetek"], "commits": [77, 21, 10, 9, 7, 7, 3, 3, 3, 3], "id": [336, 4, 78, 146, 10, 7, 340, 168, 159, 341]}}