{"authors.": {"authors": ["David Faure", "Aur\u00e9lien G\u00e2teau", "Alex Merry", "KDE Scripty", "Jenkins CI", "Kevin Ottens", "Marco Martin", "Martin Gr\u00e4\u00dflin", "Albert Astals Cid", "Cornelius Schumacher"], "commits": [24, 8, 5, 4, 2, 2, 2, 2, 1, 1], "id": [4, 73, 146, 10, 633, 203, 795, 159, 94, 634]}, "authors.last month": {"authors": ["KDE Scripty", "Marco Martin", "Denis Steckelmacher"], "commits": [3, 2, 1], "id": [10, 795, 1099]}, "authors.last year": {"authors": ["David Faure", "Aur\u00e9lien G\u00e2teau", "Alex Merry", "KDE Scripty", "Jenkins CI", "Kevin Ottens", "Marco Martin", "Martin Gr\u00e4\u00dflin", "Albert Astals Cid", "Cornelius Schumacher"], "commits": [24, 8, 5, 4, 2, 2, 2, 2, 1, 1], "id": [4, 73, 146, 10, 633, 203, 795, 159, 94, 634]}}