{"authors.": {"authors": ["Daniele E. Domenichelli", "David Edmundson", "\u00c0lex Fiestas", "Martin Klapetek", "Dario Freddi", "George Kiagiadakis", "Leon Handreke", "Dan Vr\u00e1til", "Jeremy Whiting", "Alin Elena"], "commits": [65, 39, 30, 27, 8, 6, 6, 5, 5, 4], "id": [342, 340, 78, 341, 345, 344, 355, 348, 328, 346]}, "authors.last month": {"authors": "Martin Klapetek", "commits": 16, "id": 341}, "authors.last year": {"authors": ["Martin Klapetek", "David Edmundson", "Leon Handreke", "Daniel Cohen", "Diane Trout"], "commits": [19, 8, 6, 1, 1], "id": [341, 340, 355, 356, 353]}}